{
  "places": [
    {
      "type": "Food",
      "name": "Graze",
      "location": {
        "lat": 43.075617,
        "lng": -89.382206
      },
      "yelp_business_id": "graze-madison"
    },
    {
      "type": "Food",
      "name": "Dotty Dumpling's Dowry",
      "location": {
        "lat": 43.072829,
        "lng": -89.401329
      },
      "yelp_business_id": "dotty-dumplings-dowry-madison"
    },
    {
      "type": "Food",
      "name": "Paisan's Restaurant",
      "location": {
        "lat": 43.070682,
        "lng": -89.383026
      },
      "yelp_business_id": "paisans-madison"
    },
    {
      "type": "Attraction",
      "name": "Madison Children's Museum",
      "location": {
        "lat": 43.076674,
        "lng": -89.384438
      },
      "yelp_business_id": "madison-childrens-museum-madison"
    },
    {
      "type": "Attraction",
      "name": "Camp Randall Stadium",
      "location": {
        "lat": 43.069897,
        "lng": -89.412772
      },
      "yelp_business_id": "camp-randall-stadium-madison-2"
    }
  ]
}